watchmen_storage/__init__.py
watchmen_storage/competitive_worker_id_generator.py
watchmen_storage/data_source_helper.py
watchmen_storage/free_storage_types.py
watchmen_storage/secrets_manager.py
watchmen_storage/secrets_manager_aws.py
watchmen_storage/settings.py
watchmen_storage/snowflake.py
watchmen_storage/snowflake_worker_id_generator.py
watchmen_storage/snowflake_workers.py
watchmen_storage/sql_analysis/__init__.py
watchmen_storage/sql_analysis/ast_visitor.py
watchmen_storage/sql_analysis/parse_sql.py
watchmen_storage/sql_analysis/topic_generator.py
watchmen_storage/storage_based_worker_id_generator.py
watchmen_storage/storage_based_worker_id_service.py
watchmen_storage/storage_exception.py
watchmen_storage/storage_spi.py
watchmen_storage/storage_types.py
watchmen_storage/topic_utils.py
watchmen_storage-18.0.1.dist-info/METADATA
watchmen_storage-18.0.1.dist-info/WHEEL
watchmen_storage-18.0.1.dist-info/licenses/LICENSE
watchmen_storage-18.0.1.dist-info/RECORD
